{
  "db": "PostgreSQL",
  "ed8c20c6ed9f9ef9551df6559b8d3455ccdfd5129d093c9e828f3dc540a4addc": {
    "describe": {
      "columns": [
        {
          "name": "id",
          "ordinal": 0,
          "type_info": "Int4"
        },
        {
          "name": "title",
          "ordinal": 1,
          "type_info": "Varchar"
        },
        {
          "name": "genres",
          "ordinal": 2,
          "type_info": "VarcharArray"
        },
        {
          "name": "release_year",
          "ordinal": 3,
          "type_info": "Int2"
        }
      ],
      "nullable": [
        false,
        false,
        true,
        false
      ],
      "parameters": {
        "Left": []
      }
    },
    "query": "select *\nfrom movies\norder by title;"
  }
}